wood_cpp_nano/__init__.py
wood_cpp_nano/libgmp-10.dll
wood_cpp_nano/libmpfr-4.dll
wood_cpp_nano/wood_cpp_nano_ext.pypy38-pp73-x86_64-linux-gnu.so
wood_cpp_nano-0.0.4.dist-info/METADATA
wood_cpp_nano-0.0.4.dist-info/WHEEL
wood_cpp_nano-0.0.4.dist-info/entry_points.txt
wood_cpp_nano-0.0.4.dist-info/licenses/LICENSE
wood_cpp_nano-0.0.4.dist-info/RECORD
