Metadata-Version: 2.1
Name: wood-cpp-nano
Version: 0.0.4
Summary: Binding for wood_cpp project that  is compiled into a binding using nanobind and scikit-build
Author-Email: Petras Vestartas <petrasvestartas@gmail.com>
Classifier: License :: OSI Approved :: BSD License
Project-URL: Homepage, https://github.com/petrasvestartas/wood_cpp_nano
Requires-Python: >=3.8.16
License-File: LICENSE
